wranglertools/__init__.py
wranglertools/get_field_info.py
wranglertools/import_data.py
submit4dn-5.0.1.dist-info/LICENSE.txt
submit4dn-5.0.1.dist-info/METADATA
submit4dn-5.0.1.dist-info/WHEEL
submit4dn-5.0.1.dist-info/entry_points.txt
submit4dn-5.0.1.dist-info/RECORD
