Metadata-Version: 2.1
Name: submit4dn
Version: 5.0.1
Summary: Utility package for submitting data to the 4DN Data Portal
Home-page: https://github.com/4dn-dcic/Submit4DN
License: MIT
Author: 4DN-DCIC Team
Author-email: support@4dnucleome.org
Requires-Python: >=3.9,<3.13
Classifier: License :: OSI Approved :: MIT License
Classifier: Programming Language :: Python :: 3
Classifier: Programming Language :: Python :: 3.9
Classifier: Programming Language :: Python :: 3.10
Classifier: Programming Language :: Python :: 3.11
Requires-Dist: attrs (>=22.2,<23.0)
Requires-Dist: awscli (>=1.27,<2.0)
Requires-Dist: dcicutils (>=8.13.0,<9.0.0)
Requires-Dist: openpyxl (>=3.1.2,<4.0.0)
Requires-Dist: python-magic (>=0.4.12,<1)
Project-URL: Repository, https://github.com/4dn-dcic/Submit4DN
